online_store/__init__.py
online_store/main.py
online_store/order_manager.py
online_store/user_manager.py
online_store_alexKhar-0.1.0.dist-info/METADATA
online_store_alexKhar-0.1.0.dist-info/WHEEL
online_store_alexKhar-0.1.0.dist-info/top_level.txt
online_store_alexKhar-0.1.0.dist-info/RECORD
